{
    "version": "0.4",
    "title": "Board Detail 3 &#8211; Pro",
    "type": "section",
    "metadata": {
        "template_type": "section",
        "elementor_pro_required": false,
        "wp_page_template": "default"
    },
    "content": [
        {
            "id": "2f3a6cb7",
            "settings": {
                "height": "min-height",
                "structure": "22",
                "background_background": "classic",
                "background_color": "#00405e",
                "background_image": {
                    "url": "https:\/\/wp.envatoextensions.com\/kit-71\/wp-content\/uploads\/sites\/74\/2018\/09\/teddy-kelley-105544-unsplash.jpg",
                    "id": 327
                },
                "background_overlay_background": "classic",
                "background_overlay_color": "rgba(64,84,178,0)",
                "background_overlay_color_b": "#f9a07c",
                "background_overlay_color_b_stop": {
                    "unit": "%",
                    "size": 88
                },
                "background_overlay_gradient_angle": {
                    "unit": "deg",
                    "size": 0
                },
                "background_overlay_opacity": {
                    "unit": "px",
                    "size": 0.80000000000000004
                },
                "gap": "wider",
                "background_position": "initial",
                "background_attachment": "fixed",
                "background_repeat": "repeat",
                "background_size": "cover",
                "shape_divider_bottom": "mountains",
                "shape_divider_bottom_color": "#00405e",
                "background_overlay_color_stop": {
                    "unit": "%",
                    "size": 60
                },
                "padding_mobile": {
                    "unit": "px",
                    "top": "80",
                    "right": "0",
                    "bottom": "80",
                    "left": "0",
                    "isLinked": false
                },
                "shape_divider_bottom_height": {
                    "unit": "px",
                    "size": 214
                },
                "custom_height": {
                    "unit": "vh",
                    "size": 50
                },
                "column_position": "stretch",
                "shape_divider_bottom_width": {
                    "unit": "%",
                    "size": 135
                },
                "shape_divider_bottom_flip": "yes",
                "background_ypos": {
                    "unit": "vh",
                    "size": 78
                },
                "custom_height_tablet": {
                    "unit": "px",
                    "size": 553
                },
                "background_position_tablet": "initial",
                "background_position_mobile": "center center",
                "background_xpos_tablet": {
                    "unit": "px",
                    "size": -75
                },
                "background_ypos_tablet": {
                    "unit": "vh",
                    "size": 0
                },
                "background_size_tablet": "cover",
                "shape_divider_bottom_width_tablet": {
                    "unit": "%",
                    "size": 179
                },
                "shape_divider_bottom_width_mobile": {
                    "unit": "%",
                    "size": 273
                },
                "shape_divider_bottom_height_tablet": {
                    "unit": "px",
                    "size": 177
                },
                "shape_divider_bottom_height_mobile": {
                    "unit": "px",
                    "size": 147
                },
                "reverse_order_mobile": "reverse-mobile"
            },
            "elements": [
                {
                    "id": "2c979549",
                    "settings": {
                        "_column_size": 66,
                        "_inline_size": 57.543999999999997,
                        "content_position": "center",
                        "margin_mobile": {
                            "unit": "px",
                            "top": "0",
                            "right": "0",
                            "bottom": "0",
                            "left": "0",
                            "isLinked": true
                        },
                        "padding_mobile": {
                            "unit": "px",
                            "top": "0",
                            "right": "0",
                            "bottom": "0",
                            "left": "0",
                            "isLinked": true
                        }
                    },
                    "elements": [],
                    "isInner": false,
                    "elType": "column"
                },
                {
                    "id": "2072e8a3",
                    "settings": {
                        "_column_size": 33,
                        "_inline_size": 42.453000000000003,
                        "content_position": "center"
                    },
                    "elements": [
                        {
                            "id": "4832ac22",
                            "settings": {
                                "title": "Boards",
                                "size": "xxl",
                                "header_size": "h1",
                                "title_color": "#ffffff",
                                "typography_typography": "custom",
                                "typography_font_family": "Fugaz One",
                                "typography_letter_spacing": {
                                    "unit": "px",
                                    "size": -5
                                },
                                "_margin": {
                                    "unit": "px",
                                    "top": "0",
                                    "right": "0",
                                    "bottom": "0",
                                    "left": "0",
                                    "isLinked": false
                                },
                                "typography_font_size": {
                                    "unit": "rem",
                                    "size": 7.9000000000000004
                                },
                                "typography_font_size_mobile": {
                                    "unit": "px",
                                    "size": 79
                                },
                                "_margin_mobile": {
                                    "unit": "px",
                                    "top": "0",
                                    "right": "0",
                                    "bottom": "0",
                                    "left": "0",
                                    "isLinked": true
                                },
                                "align": "left",
                                "typography_font_size_tablet": {
                                    "unit": "px",
                                    "size": 86
                                },
                                "typography_line_height": {
                                    "unit": "em",
                                    "size": 0.90000000000000002
                                },
                                "_margin_tablet": {
                                    "unit": "px",
                                    "top": "0",
                                    "right": "0",
                                    "bottom": "0",
                                    "left": "0",
                                    "isLinked": false
                                },
                                "_padding": {
                                    "unit": "em",
                                    "top": "",
                                    "right": "",
                                    "bottom": "",
                                    "left": "",
                                    "isLinked": true
                                },
                                "_padding_mobile": {
                                    "unit": "px",
                                    "top": "1",
                                    "right": "20",
                                    "bottom": "8",
                                    "left": "20",
                                    "isLinked": false
                                },
                                "_z_index": 1,
                                "_background_color": "#ffffff"
                            },
                            "elements": [],
                            "isInner": false,
                            "widgetType": "heading",
                            "elType": "widget"
                        },
                        {
                            "id": "66b2fc8c",
                            "settings": {
                                "text": "Shop Collection",
                                "size": "lg",
                                "typography_typography": "custom",
                                "typography_font_family": "Lato",
                                "typography_font_weight": "700",
                                "typography_text_transform": "uppercase",
                                "button_text_color": "#ffffff",
                                "background_color": "rgba(249,160,124,0)",
                                "hover_color": "#ffffff",
                                "button_background_hover_color": "rgba(255,255,255,0)",
                                "button_hover_border_color": "#0063a0",
                                "border_width": {
                                    "unit": "px",
                                    "top": "2",
                                    "right": "2",
                                    "bottom": "2",
                                    "left": "2",
                                    "isLinked": true
                                },
                                "border_color": "#fba888",
                                "border_radius": {
                                    "unit": "px",
                                    "top": "35",
                                    "right": "35",
                                    "bottom": "35",
                                    "left": "35",
                                    "isLinked": true
                                },
                                "align": "center",
                                "icon": "fa fa-long-arrow-right",
                                "icon_align": "right",
                                "icon_indent": {
                                    "unit": "px",
                                    "size": 10
                                },
                                "typography_font_size_mobile": {
                                    "unit": "px",
                                    "size": 17
                                },
                                "typography_letter_spacing": {
                                    "unit": "px",
                                    "size": 1
                                },
                                "button_box_shadow_box_shadow": {
                                    "horizontal": 2,
                                    "vertical": 2,
                                    "blur": 0,
                                    "spread": 0,
                                    "color": "#ffffff"
                                },
                                "text_padding_mobile": {
                                    "unit": "px",
                                    "top": "16",
                                    "right": "35",
                                    "bottom": "16",
                                    "left": "35",
                                    "isLinked": false
                                },
                                "align_mobile": "center",
                                "typography_font_size": {
                                    "unit": "rem",
                                    "size": 1.1000000000000001
                                },
                                "typography_font_size_tablet": {
                                    "unit": "px",
                                    "size": 15
                                },
                                "_margin": {
                                    "unit": "px",
                                    "top": "0",
                                    "right": "0",
                                    "bottom": "0",
                                    "left": "0",
                                    "isLinked": false
                                },
                                "_background_background": "classic",
                                "_background_image": {
                                    "url": "https:\/\/wp.envatoextensions.com\/kit-71\/wp-content\/uploads\/sites\/74\/2018\/09\/beachy2-bg.jpg",
                                    "id": 783
                                },
                                "_background_size": "cover",
                                "_background_hover_background": "classic",
                                "_background_hover_image": {
                                    "url": "https:\/\/wp.envatoextensions.com\/kit-71\/wp-content\/uploads\/sites\/74\/2018\/09\/beachy2-bg.jpg",
                                    "id": 783
                                },
                                "_background_hover_position": "initial",
                                "_background_hover_xpos": {
                                    "unit": "px",
                                    "size": -50
                                },
                                "_background_hover_ypos": {
                                    "unit": "px",
                                    "size": -128
                                },
                                "_background_hover_size": "auto",
                                "_background_hover_transition": {
                                    "unit": "px",
                                    "size": 0.5
                                },
                                "_border_width": {
                                    "unit": "px",
                                    "top": "2",
                                    "right": "2",
                                    "bottom": "2",
                                    "left": "2",
                                    "isLinked": true
                                },
                                "_border_color": "#000000",
                                "_border_radius": {
                                    "unit": "px",
                                    "top": "30",
                                    "right": "30",
                                    "bottom": "30",
                                    "left": "30",
                                    "isLinked": true
                                },
                                "_box_shadow_box_shadow": {
                                    "horizontal": 3,
                                    "vertical": 3,
                                    "blur": 0,
                                    "spread": 0,
                                    "color": "#0027b5"
                                },
                                "_z_index": 11,
                                "selected_icon": {
                                    "value": "fas fa-long-arrow-alt-right",
                                    "library": "fa-solid"
                                }
                            },
                            "elements": [],
                            "isInner": false,
                            "widgetType": "button",
                            "elType": "widget"
                        }
                    ],
                    "isInner": false,
                    "elType": "column"
                }
            ],
            "isInner": false,
            "elType": "section"
        },
        {
            "id": "3b420066",
            "settings": {
                "structure": "20",
                "background_background": "classic",
                "background_color": "#fff7f1",
                "background_overlay_color": "rgba(64,84,178,0.33)",
                "background_overlay_color_b": "#0027b5",
                "background_overlay_color_b_stop": {
                    "unit": "%",
                    "size": 57
                },
                "background_overlay_gradient_angle": {
                    "unit": "deg",
                    "size": 140
                },
                "background_overlay_opacity": {
                    "unit": "px",
                    "size": 0.68000000000000005
                },
                "gap": "no",
                "background_position": "center center",
                "background_attachment": "fixed",
                "background_repeat": "repeat",
                "background_size": "cover",
                "shape_divider_bottom_color": "#f9c700",
                "content_position": "middle",
                "padding": {
                    "unit": "%",
                    "top": "6",
                    "right": "0",
                    "bottom": "4",
                    "left": "0",
                    "isLinked": false
                },
                "shape_divider_bottom_width": {
                    "unit": "%",
                    "size": 120
                },
                "shape_divider_bottom_height": {
                    "unit": "px",
                    "size": 200
                },
                "padding_tablet": {
                    "unit": "px",
                    "top": "0",
                    "right": "0",
                    "bottom": "0",
                    "left": "0",
                    "isLinked": false
                },
                "padding_mobile": {
                    "unit": "px",
                    "top": "30",
                    "right": "0",
                    "bottom": "30",
                    "left": "0",
                    "isLinked": false
                },
                "margin": {
                    "unit": "px",
                    "top": "0",
                    "right": 0,
                    "bottom": "0",
                    "left": 0,
                    "isLinked": false
                },
                "shape_divider_top": "mountains",
                "shape_divider_top_color": "#00405e",
                "shape_divider_top_width": {
                    "unit": "%",
                    "size": 300
                },
                "shape_divider_top_height": {
                    "unit": "px",
                    "size": 365
                },
                "shape_divider_top_flip": "yes",
                "shape_divider_top_height_tablet": {
                    "unit": "px",
                    "size": 137
                }
            },
            "elements": [
                {
                    "id": "5187ff",
                    "settings": {
                        "_column_size": 50,
                        "_inline_size": null,
                        "padding": {
                            "unit": "em",
                            "top": "4",
                            "right": "4",
                            "bottom": "4",
                            "left": "4",
                            "isLinked": true
                        },
                        "content_position": "bottom",
                        "padding_tablet": {
                            "unit": "em",
                            "top": "6",
                            "right": "1",
                            "bottom": "3",
                            "left": "1",
                            "isLinked": false
                        }
                    },
                    "elements": [
                        {
                            "id": "775912a3",
                            "settings": {
                                "title": "Brand Name",
                                "size": "medium",
                                "header_size": "h3",
                                "align": "left",
                                "title_color": "#1e5694",
                                "typography_typography": "custom",
                                "typography_font_family": "Fugaz One",
                                "typography_font_size": {
                                    "unit": "px",
                                    "size": 24
                                },
                                "typography_font_weight": "400",
                                "typography_font_style": "italic",
                                "_margin": {
                                    "unit": "px",
                                    "top": "0",
                                    "right": "0",
                                    "bottom": "-10",
                                    "left": "0",
                                    "isLinked": false
                                },
                                "typography_text_transform": "capitalize"
                            },
                            "elements": [],
                            "isInner": false,
                            "widgetType": "heading",
                            "elType": "widget"
                        },
                        {
                            "id": "442779d5",
                            "settings": {
                                "title": "Great White XL",
                                "size": "xxl",
                                "header_size": "h1",
                                "title_color": "#00405e",
                                "typography_typography": "custom",
                                "typography_font_family": "Lato",
                                "typography_letter_spacing": {
                                    "unit": "px",
                                    "size": -5
                                },
                                "_margin": {
                                    "unit": "px",
                                    "top": "0",
                                    "right": "0",
                                    "bottom": "52",
                                    "left": "0",
                                    "isLinked": false
                                },
                                "typography_font_size": {
                                    "unit": "rem",
                                    "size": 3.7999999999999998
                                },
                                "typography_font_size_mobile": {
                                    "unit": "px",
                                    "size": 51
                                },
                                "align": "left",
                                "typography_font_size_tablet": {
                                    "unit": "px",
                                    "size": 52
                                },
                                "typography_line_height": {
                                    "unit": "em",
                                    "size": 1.1000000000000001
                                },
                                "_margin_tablet": {
                                    "unit": "px",
                                    "top": "0",
                                    "right": "0",
                                    "bottom": "0",
                                    "left": "0",
                                    "isLinked": false
                                },
                                "_margin_mobile": {
                                    "unit": "px",
                                    "top": "0",
                                    "right": "0",
                                    "bottom": "0",
                                    "left": "0",
                                    "isLinked": true
                                },
                                "_padding": {
                                    "unit": "em",
                                    "top": "",
                                    "right": "",
                                    "bottom": "",
                                    "left": "",
                                    "isLinked": true
                                },
                                "_padding_mobile": {
                                    "unit": "px",
                                    "top": "1",
                                    "right": "0",
                                    "bottom": "8",
                                    "left": "0",
                                    "isLinked": false
                                },
                                "_z_index": 1,
                                "_background_color": "#ffffff"
                            },
                            "elements": [],
                            "isInner": false,
                            "widgetType": "heading",
                            "elType": "widget"
                        },
                        {
                            "id": "3372b400",
                            "settings": {
                                "text_color": "#00405e",
                                "typography_typography": "custom",
                                "typography_font_family": "Lato",
                                "typography_font_size": {
                                    "unit": "px",
                                    "size": 20
                                },
                                "typography_line_height": {
                                    "unit": "em",
                                    "size": 1.6000000000000001
                                },
                                "_margin": {
                                    "unit": "px",
                                    "top": "0",
                                    "right": "0",
                                    "bottom": "31",
                                    "left": "0",
                                    "isLinked": false
                                },
                                "typography_font_size_mobile": {
                                    "unit": "px",
                                    "size": 16
                                },
                                "typography_font_weight": "500",
                                "editor": "<p>Lorem ipsum dolor sit amet, consectetur adipiscing elit. Ut elit tellus, luctus nec ullamcorper mattis, pulvinar dapibus leo.\u00a0Excepteur sint occaecat cupidatat non proident, sunt in culpa qui officia deserunt mollit anim id est laborum.<\/p>",
                                "align": "left",
                                "typography_font_size_tablet": {
                                    "unit": "px",
                                    "size": 16
                                },
                                "typography_line_height_tablet": {
                                    "unit": "em",
                                    "size": 1.6000000000000001
                                }
                            },
                            "elements": [],
                            "isInner": false,
                            "widgetType": "text-editor",
                            "elType": "widget"
                        },
                        {
                            "id": "780a7043",
                            "settings": {
                                "text": "$1,650 - Buy Now",
                                "size": "lg",
                                "typography_typography": "custom",
                                "typography_font_family": "Lato",
                                "typography_font_weight": "700",
                                "typography_text_transform": "uppercase",
                                "button_text_color": "#0063a0",
                                "background_color": "#d1f5ed",
                                "hover_color": "#00405e",
                                "button_background_hover_color": "rgba(255,255,255,0)",
                                "button_hover_border_color": "#00405e",
                                "border_border": "solid",
                                "border_width": {
                                    "unit": "px",
                                    "top": "2",
                                    "right": "2",
                                    "bottom": "2",
                                    "left": "2",
                                    "isLinked": true
                                },
                                "border_color": "#d1f5ed",
                                "border_radius": {
                                    "unit": "px",
                                    "top": "35",
                                    "right": "35",
                                    "bottom": "35",
                                    "left": "35",
                                    "isLinked": true
                                },
                                "text_padding": {
                                    "unit": "px",
                                    "top": "20",
                                    "right": "35",
                                    "bottom": "20",
                                    "left": "55",
                                    "isLinked": false
                                },
                                "icon": "fa fa-long-arrow-right",
                                "icon_align": "right",
                                "icon_indent": {
                                    "unit": "px",
                                    "size": 10
                                },
                                "typography_font_size_mobile": {
                                    "unit": "px",
                                    "size": 16
                                },
                                "typography_letter_spacing": {
                                    "unit": "px",
                                    "size": 0.5
                                },
                                "button_box_shadow_box_shadow": {
                                    "horizontal": 2,
                                    "vertical": 2,
                                    "blur": 0,
                                    "spread": 0,
                                    "color": "#ffffff"
                                },
                                "text_padding_mobile": {
                                    "unit": "px",
                                    "top": "16",
                                    "right": "35",
                                    "bottom": "16",
                                    "left": "35",
                                    "isLinked": false
                                },
                                "align": "left",
                                "align_mobile": "left",
                                "selected_icon": {
                                    "value": "fas fa-long-arrow-alt-right",
                                    "library": "fa-solid"
                                }
                            },
                            "elements": [],
                            "isInner": false,
                            "widgetType": "button",
                            "elType": "widget"
                        },
                        {
                            "id": "51f68a41",
                            "settings": {
                                "tabs": [
                                    {
                                        "tab_title": "Info",
                                        "tab_content": "<ul><li>High-performance fish shape and rocker<\/li><li>Twin wood Stringers and Dual-composite core of high-pressure construction for maximum stiffness<\/li><li>High density Slick bottom<\/li><li>Special 4.5 inch performance thruster fin set<\/li><li>Requires surf wax<\/li><\/ul>",
                                        "_id": "10cafea"
                                    },
                                    {
                                        "tab_title": "Specs",
                                        "tab_content": "<p><strong>Shipping Weight:<\/strong><br \/>16 pounds (View shipping rates and policies)<\/p><p><strong>Domestic Shipping:<\/strong><br \/>Item can be shipped within U.S.<\/p><p><strong>International Shipping:<\/strong><br \/>This item is not eligible for international shipping.\u00a0<\/p><p><strong>ASIN:<\/strong><br \/>B01N1YQNX8<\/p><p><strong>Item model number:<\/strong><br \/>WB66<\/p>",
                                        "_id": "dc61c5e"
                                    }
                                ],
                                "tab_typography_typography": "custom",
                                "tab_typography_font_family": "Lato",
                                "content_typography_typography": "custom",
                                "content_typography_font_size": {
                                    "unit": "rem",
                                    "size": 1
                                },
                                "tab_color": "#00405e",
                                "tab_active_color": "#1e5694",
                                "tab_typography_font_weight": "bold",
                                "tab_typography_text_transform": "uppercase",
                                "content_color": "rgba(0,64,94,0.76)",
                                "content_typography_line_height": {
                                    "unit": "em",
                                    "size": 2
                                },
                                "_margin": {
                                    "unit": "px",
                                    "top": "40",
                                    "right": "0",
                                    "bottom": "0",
                                    "left": "0",
                                    "isLinked": false
                                },
                                "border_width": {
                                    "unit": "px",
                                    "size": 2
                                },
                                "border_color": "rgba(0,0,0,0.06)",
                                "content_typography_font_family": "Lato",
                                "_css_classes": "envato-kit-71-tab-radius",
                                "_border_radius": {
                                    "unit": "px",
                                    "top": "11",
                                    "right": "11",
                                    "bottom": "11",
                                    "left": "11",
                                    "isLinked": true
                                }
                            },
                            "elements": [],
                            "isInner": false,
                            "widgetType": "tabs",
                            "elType": "widget"
                        }
                    ],
                    "isInner": false,
                    "elType": "column"
                },
                {
                    "id": "1628a079",
                    "settings": {
                        "_column_size": 50,
                        "_inline_size": null,
                        "background_background": "classic",
                        "background_image": {
                            "url": "https:\/\/wp.envatoextensions.com\/kit-71\/wp-content\/uploads\/sites\/74\/2018\/09\/beachy2-bg.jpg",
                            "id": 783
                        },
                        "margin": {
                            "unit": "px",
                            "top": "0",
                            "right": "0",
                            "bottom": "0",
                            "left": "0",
                            "isLinked": false
                        },
                        "padding": {
                            "unit": "em",
                            "top": "2",
                            "right": "2",
                            "bottom": "2",
                            "left": "2",
                            "isLinked": true
                        },
                        "border_radius": {
                            "unit": "px",
                            "top": "20",
                            "right": "20",
                            "bottom": "20",
                            "left": "20",
                            "isLinked": true
                        },
                        "margin_tablet": {
                            "unit": "px",
                            "top": "90",
                            "right": "0",
                            "bottom": "90",
                            "left": "0",
                            "isLinked": false
                        },
                        "margin_mobile": {
                            "unit": "px",
                            "top": "0",
                            "right": "0",
                            "bottom": "0",
                            "left": "0",
                            "isLinked": true
                        },
                        "padding_tablet": {
                            "unit": "px",
                            "top": "0",
                            "right": "0",
                            "bottom": "0",
                            "left": "0",
                            "isLinked": true
                        },
                        "padding_mobile": {
                            "unit": "em",
                            "top": "1",
                            "right": "1",
                            "bottom": "1",
                            "left": "1",
                            "isLinked": true
                        }
                    },
                    "elements": [
                        {
                            "id": "6e3eabc",
                            "settings": {
                                "carousel": [
                                    {
                                        "id": 54,
                                        "url": "https:\/\/wp.envatoextensions.com\/kit-71\/wp-content\/uploads\/sites\/74\/2018\/09\/roman-raizen-674547-unsplash.jpg"
                                    },
                                    {
                                        "id": 786,
                                        "url": "https:\/\/wp.envatoextensions.com\/kit-71\/wp-content\/uploads\/sites\/74\/2018\/09\/pexels-photo-1546116.jpeg"
                                    },
                                    {
                                        "id": 785,
                                        "url": "https:\/\/wp.envatoextensions.com\/kit-71\/wp-content\/uploads\/sites\/74\/2018\/09\/pexels-photo-1394264.jpeg"
                                    }
                                ],
                                "thumbnail_size": "custom",
                                "thumbnail_custom_dimension": {
                                    "width": "800",
                                    "height": "1200"
                                },
                                "slides_to_show": "1",
                                "_box_shadow_box_shadow_type": "yes",
                                "_box_shadow_box_shadow": {
                                    "horizontal": -6,
                                    "vertical": 6,
                                    "blur": 37,
                                    "spread": 0,
                                    "color": "rgba(252,226,191,0.22)"
                                },
                                "arrows_size": {
                                    "unit": "px",
                                    "size": 60
                                },
                                "arrows_color": "#0027b5",
                                "dots_position": "inside",
                                "dots_size": {
                                    "unit": "px",
                                    "size": 10
                                },
                                "dots_color": "#0027b5",
                                "_margin": {
                                    "unit": "px",
                                    "top": "-50",
                                    "right": "-45",
                                    "bottom": "0",
                                    "left": "0",
                                    "isLinked": false
                                },
                                "_padding": {
                                    "unit": "px",
                                    "top": "0",
                                    "right": "0",
                                    "bottom": "0",
                                    "left": "0",
                                    "isLinked": true
                                },
                                "image_border_radius": {
                                    "unit": "px",
                                    "top": "20",
                                    "right": "20",
                                    "bottom": "20",
                                    "left": "20",
                                    "isLinked": true
                                },
                                "_margin_tablet": {
                                    "unit": "px",
                                    "top": "0",
                                    "right": "0",
                                    "bottom": "0",
                                    "left": "0",
                                    "isLinked": true
                                },
                                "_padding_tablet": {
                                    "unit": "px",
                                    "top": "0",
                                    "right": "0",
                                    "bottom": "0",
                                    "left": "0",
                                    "isLinked": true
                                }
                            },
                            "elements": [],
                            "isInner": false,
                            "widgetType": "image-carousel",
                            "elType": "widget"
                        }
                    ],
                    "isInner": false,
                    "elType": "column"
                }
            ],
            "isInner": false,
            "elType": "section"
        },
        {
            "id": "3eb87b4a",
            "settings": {
                "height": "min-height",
                "background_background": "video",
                "background_color": "#7a7a7a",
                "background_image": {
                    "url": "https:\/\/wp.envatoextensions.com\/kit-71\/wp-content\/uploads\/sites\/74\/2018\/09\/nicole-honeywill-727770-unsplash.jpg",
                    "id": 10
                },
                "background_overlay_background": "gradient",
                "background_overlay_color": "#e2c5a7",
                "background_overlay_color_b": "#00405e",
                "background_overlay_color_b_stop": {
                    "unit": "%",
                    "size": 57
                },
                "background_overlay_gradient_angle": {
                    "unit": "deg",
                    "size": 140
                },
                "background_overlay_opacity": {
                    "unit": "px",
                    "size": 0.68000000000000005
                },
                "gap": "wider",
                "background_position": "center center",
                "background_attachment": "fixed",
                "background_repeat": "repeat",
                "background_size": "cover",
                "shape_divider_bottom_color": "#00405e",
                "background_video_link": "https:\/\/www.youtube.com\/watch?v=kHsFhFtWm9o&",
                "background_video_start": 46,
                "background_video_end": 180,
                "padding": {
                    "unit": "px",
                    "top": "120",
                    "right": "0",
                    "bottom": "120",
                    "left": "0",
                    "isLinked": false
                },
                "padding_mobile": {
                    "unit": "px",
                    "top": "60",
                    "right": "0",
                    "bottom": "60",
                    "left": "0",
                    "isLinked": false
                },
                "content_width": {
                    "unit": "px",
                    "size": 940
                },
                "shape_divider_bottom": "mountains",
                "shape_divider_bottom_width": {
                    "unit": "%",
                    "size": 165
                },
                "shape_divider_bottom_height": {
                    "unit": "px",
                    "size": 148
                },
                "custom_height": {
                    "unit": "px",
                    "size": 450
                },
                "shape_divider_top": "mountains",
                "shape_divider_top_color": "#fff7f1",
                "shape_divider_top_width": {
                    "unit": "%",
                    "size": 165
                },
                "shape_divider_top_height": {
                    "unit": "px",
                    "size": 108
                },
                "shape_divider_top_flip": "yes",
                "shape_divider_top_width_mobile": {
                    "unit": "%",
                    "size": 282
                },
                "shape_divider_bottom_width_mobile": {
                    "unit": "%",
                    "size": 300
                }
            },
            "elements": [
                {
                    "id": "476aed28",
                    "settings": {
                        "_column_size": 100,
                        "_inline_size": null,
                        "padding": {
                            "unit": "em",
                            "top": "2",
                            "right": "2",
                            "bottom": "2",
                            "left": "2",
                            "isLinked": true
                        }
                    },
                    "elements": [
                        {
                            "id": "628f4c82",
                            "settings": [],
                            "elements": [],
                            "isInner": false,
                            "widgetType": "spacer",
                            "elType": "widget"
                        }
                    ],
                    "isInner": false,
                    "elType": "column"
                }
            ],
            "isInner": false,
            "elType": "section"
        },
        {
            "id": "3272033",
            "settings": {
                "background_background": "classic",
                "background_color": "#00405e",
                "background_overlay_background": "classic",
                "background_overlay_color": "#0063a0",
                "background_overlay_color_b": "#0027b5",
                "background_overlay_gradient_angle": {
                    "unit": "deg",
                    "size": 10
                },
                "background_overlay_opacity": {
                    "unit": "px",
                    "size": 0.14000000000000001
                },
                "gap": "wider",
                "content_position": "middle",
                "background_position": "center center",
                "background_attachment": "fixed",
                "background_repeat": "repeat",
                "background_size": "cover",
                "shape_divider_bottom_color": "rgba(255,255,255,0.11)",
                "padding": {
                    "unit": "%",
                    "top": "2",
                    "right": "0",
                    "bottom": "2",
                    "left": "0",
                    "isLinked": false
                },
                "padding_mobile": {
                    "unit": "px",
                    "top": "60",
                    "right": "0",
                    "bottom": "60",
                    "left": "0",
                    "isLinked": false
                },
                "background_overlay_color_stop": {
                    "unit": "%",
                    "size": 20
                },
                "structure": "20",
                "background_overlay_image": {
                    "url": "https:\/\/wp.envatoextensions.com\/kit-71\/wp-content\/uploads\/sites\/74\/2018\/09\/michael-olsen-465727-unsplash.jpg",
                    "id": 322
                },
                "css_filters_css_filter": "custom",
                "css_filters_hue": {
                    "unit": "px",
                    "size": 33
                }
            },
            "elements": [
                {
                    "id": "1e0ed809",
                    "settings": {
                        "_column_size": 50,
                        "_inline_size": null
                    },
                    "elements": [
                        {
                            "id": "7c2f741a",
                            "settings": {
                                "content_width": {
                                    "unit": "px",
                                    "size": 900
                                }
                            },
                            "elements": [
                                {
                                    "id": "168e8506",
                                    "settings": {
                                        "_column_size": 100,
                                        "_inline_size": null,
                                        "padding": {
                                            "unit": "px",
                                            "top": "0",
                                            "right": "0",
                                            "bottom": "40",
                                            "left": "0",
                                            "isLinked": false
                                        }
                                    },
                                    "elements": [
                                        {
                                            "id": "72c50e59",
                                            "settings": {
                                                "title": "Early-season Sale",
                                                "size": "large",
                                                "title_color": "#fba888",
                                                "typography_typography": "custom",
                                                "typography_font_family": "Fugaz One",
                                                "typography_font_weight": "400",
                                                "_margin": {
                                                    "unit": "px",
                                                    "top": "0",
                                                    "right": "0",
                                                    "bottom": "-10",
                                                    "left": "0",
                                                    "isLinked": false
                                                },
                                                "align": "left",
                                                "typography_text_transform": "capitalize",
                                                "typography_font_size": {
                                                    "unit": "px",
                                                    "size": 24
                                                },
                                                "typography_font_style": "italic",
                                                "align_mobile": "center"
                                            },
                                            "elements": [],
                                            "isInner": false,
                                            "widgetType": "heading",
                                            "elType": "widget"
                                        },
                                        {
                                            "id": "9a0c37e",
                                            "settings": {
                                                "title": "Choose your surfboard now!",
                                                "size": "xxl",
                                                "title_color": "#ffffff",
                                                "typography_typography": "custom",
                                                "typography_font_family": "Lato",
                                                "typography_letter_spacing": {
                                                    "unit": "px",
                                                    "size": -5
                                                },
                                                "_margin": {
                                                    "unit": "px",
                                                    "top": "0",
                                                    "right": "0",
                                                    "bottom": "0",
                                                    "left": "0",
                                                    "isLinked": false
                                                },
                                                "align": "left",
                                                "typography_font_size_mobile": {
                                                    "unit": "px",
                                                    "size": 50
                                                },
                                                "typography_font_size": {
                                                    "unit": "rem",
                                                    "size": 3.7999999999999998
                                                },
                                                "typography_font_size_tablet": {
                                                    "unit": "px",
                                                    "size": 52
                                                },
                                                "typography_line_height": {
                                                    "unit": "em",
                                                    "size": 1.1000000000000001
                                                },
                                                "_margin_tablet": {
                                                    "unit": "px",
                                                    "top": "0",
                                                    "right": "0",
                                                    "bottom": "0",
                                                    "left": "0",
                                                    "isLinked": false
                                                },
                                                "_margin_mobile": {
                                                    "unit": "px",
                                                    "top": "0",
                                                    "right": "0",
                                                    "bottom": "0",
                                                    "left": "0",
                                                    "isLinked": true
                                                },
                                                "_padding": {
                                                    "unit": "em",
                                                    "top": "",
                                                    "right": "",
                                                    "bottom": "",
                                                    "left": "",
                                                    "isLinked": true
                                                },
                                                "_padding_mobile": {
                                                    "unit": "px",
                                                    "top": "1",
                                                    "right": "0",
                                                    "bottom": "8",
                                                    "left": "0",
                                                    "isLinked": false
                                                },
                                                "_z_index": 1,
                                                "_background_color": "#ffffff",
                                                "align_mobile": "center"
                                            },
                                            "elements": [],
                                            "isInner": false,
                                            "widgetType": "heading",
                                            "elType": "widget"
                                        },
                                        {
                                            "id": "38397076",
                                            "settings": {
                                                "editor": "<p>From $199 Sale-off this week only.<\/p>",
                                                "align": "left",
                                                "text_color": "#ffffff",
                                                "typography_typography": "custom",
                                                "typography_font_family": "Lato",
                                                "typography_font_size": {
                                                    "unit": "px",
                                                    "size": 22
                                                },
                                                "typography_line_height": {
                                                    "unit": "em",
                                                    "size": 1.3999999999999999
                                                },
                                                "typography_letter_spacing": {
                                                    "unit": "px",
                                                    "size": 1
                                                },
                                                "typography_font_style": "italic",
                                                "typography_font_size_mobile": {
                                                    "unit": "px",
                                                    "size": 17
                                                },
                                                "align_mobile": "center",
                                                "typography_font_size_tablet": {
                                                    "unit": "px",
                                                    "size": 19
                                                }
                                            },
                                            "elements": [],
                                            "isInner": false,
                                            "widgetType": "text-editor",
                                            "elType": "widget"
                                        }
                                    ],
                                    "isInner": true,
                                    "elType": "column"
                                }
                            ],
                            "isInner": true,
                            "elType": "section"
                        }
                    ],
                    "isInner": false,
                    "elType": "column"
                },
                {
                    "id": "7bacd195",
                    "settings": {
                        "_column_size": 50,
                        "_inline_size": null
                    },
                    "elements": [
                        {
                            "id": "4fd482a7",
                            "settings": {
                                "carousel": [
                                    {
                                        "id": 55,
                                        "url": "https:\/\/wp.envatoextensions.com\/kit-71\/wp-content\/uploads\/sites\/74\/2018\/09\/tyler-nix-691377-unsplash.jpg"
                                    },
                                    {
                                        "id": 53,
                                        "url": "https:\/\/wp.envatoextensions.com\/kit-71\/wp-content\/uploads\/sites\/74\/2018\/09\/joseph-greve-343334-unsplash.jpg"
                                    },
                                    {
                                        "id": 35,
                                        "url": "https:\/\/wp.envatoextensions.com\/kit-71\/wp-content\/uploads\/sites\/74\/2018\/09\/paul-larkin-501616-unsplash.jpg"
                                    },
                                    {
                                        "id": 10,
                                        "url": "https:\/\/wp.envatoextensions.com\/kit-71\/wp-content\/uploads\/sites\/74\/2018\/09\/nicole-honeywill-727770-unsplash.jpg"
                                    },
                                    {
                                        "id": 39,
                                        "url": "https:\/\/wp.envatoextensions.com\/kit-71\/wp-content\/uploads\/sites\/74\/2018\/09\/chris-osmond-385532-unsplash.jpg"
                                    },
                                    {
                                        "id": 44,
                                        "url": "https:\/\/wp.envatoextensions.com\/kit-71\/wp-content\/uploads\/sites\/74\/2018\/09\/carlos-augusto-588715-unsplash.jpg"
                                    },
                                    {
                                        "id": 54,
                                        "url": "https:\/\/wp.envatoextensions.com\/kit-71\/wp-content\/uploads\/sites\/74\/2018\/09\/roman-raizen-674547-unsplash.jpg"
                                    }
                                ],
                                "thumbnail_size": "custom",
                                "thumbnail_custom_dimension": {
                                    "width": "300",
                                    "height": "300"
                                },
                                "slides_to_show": "3",
                                "image_stretch": "yes",
                                "arrows_position": "outside",
                                "arrows_color": "#f98759",
                                "dots_size": {
                                    "unit": "px",
                                    "size": 6
                                },
                                "dots_color": "#f98759",
                                "image_spacing": "custom",
                                "_margin": {
                                    "unit": "px",
                                    "top": "0",
                                    "right": "20",
                                    "bottom": "0",
                                    "left": "20",
                                    "isLinked": false
                                },
                                "image_border_radius": {
                                    "unit": "px",
                                    "top": "20",
                                    "right": "20",
                                    "bottom": "20",
                                    "left": "20",
                                    "isLinked": true
                                }
                            },
                            "elements": [],
                            "isInner": false,
                            "widgetType": "image-carousel",
                            "elType": "widget"
                        }
                    ],
                    "isInner": false,
                    "elType": "column"
                }
            ],
            "isInner": false,
            "elType": "section"
        },
        {
            "id": "444493ca",
            "settings": {
                "background_background": "classic",
                "background_image": {
                    "url": "https:\/\/wp.envatoextensions.com\/kit-71\/wp-content\/uploads\/sites\/74\/2018\/09\/beachy2-bg.jpg",
                    "id": 783
                },
                "background_position": "initial",
                "background_ypos": {
                    "unit": "px",
                    "size": -150
                },
                "background_size": "auto",
                "padding": {
                    "unit": "em",
                    "top": "2",
                    "right": "2",
                    "bottom": "2",
                    "left": "2",
                    "isLinked": true
                }
            },
            "elements": [
                {
                    "id": "6b3daba3",
                    "settings": {
                        "_column_size": 100
                    },
                    "elements": [
                        {
                            "id": "5d3deae5",
                            "settings": {
                                "social_icon_list": [
                                    {
                                        "social": "fa fa-facebook",
                                        "_id": "21b533f",
                                        "link": {
                                            "url": "",
                                            "is_external": "true",
                                            "nofollow": ""
                                        }
                                    },
                                    {
                                        "social": "fa fa-twitter",
                                        "_id": "b581b37",
                                        "link": {
                                            "url": "",
                                            "is_external": "true",
                                            "nofollow": ""
                                        }
                                    },
                                    {
                                        "social": "fa fa-instagram",
                                        "link": {
                                            "url": "",
                                            "is_external": "true",
                                            "nofollow": ""
                                        },
                                        "_id": "15ded7a"
                                    },
                                    {
                                        "social": "fa fa-youtube",
                                        "link": {
                                            "url": "",
                                            "is_external": "true",
                                            "nofollow": ""
                                        },
                                        "_id": "0cc7b20"
                                    }
                                ],
                                "shape": "circle",
                                "icon_size": {
                                    "unit": "px",
                                    "size": 20
                                },
                                "icon_padding": {
                                    "unit": "em",
                                    "size": 0.80000000000000004
                                },
                                "icon_spacing": {
                                    "unit": "px",
                                    "size": 15
                                },
                                "align_mobile": "center",
                                "icon_color": "custom",
                                "icon_primary_color": "#f98e63",
                                "hover_primary_color": "#001e3d",
                                "align": "left"
                            },
                            "elements": [],
                            "isInner": false,
                            "widgetType": "social-icons",
                            "elType": "widget"
                        }
                    ],
                    "isInner": false,
                    "elType": "column"
                }
            ],
            "isInner": false,
            "elType": "section"
        }
    ]
}